GeniusDeveloper/_init_.py
Hacker_stt-1.0.dist-info/METADATA
Hacker_stt-1.0.dist-info/WHEEL
Hacker_stt-1.0.dist-info/top_level.txt
Hacker_stt-1.0.dist-info/RECORD
