Metadata-Version: 2.1
Name: Hacker-stt
Version: 1.0
Summary: This is text to speech package created by Himanshu
Home-page: https://pypi.org/project/GeniusDeveloper/
Author: Himanshu Kumar Sah
Author-email: geniusdeveloper46@gmail.com
